multispaeti/__init__.py
multispaeti/_multispati_pca.py
multispaeti/_plotting.py
multispaeti-1.2.0.dist-info/licenses/LICENSE
multispaeti-1.2.0.dist-info/METADATA
multispaeti-1.2.0.dist-info/WHEEL
multispaeti-1.2.0.dist-info/top_level.txt
multispaeti-1.2.0.dist-info/RECORD
