Metadata-Version: 2.4
Name: multispaeti
Version: 1.2.0
Summary: Implementation of MULTISPATI-PCA in python
Author-email: Niklas Müller-Bötticher <niklas.mueller-boetticher@charite.de>
License: MIT License
Project-URL: Homepage, https://github.com/HiDiHlabs/multiSPAETI
Project-URL: Documentation, https://multispaeti.readthedocs.io
Project-URL: Repository, https://github.com/HiDiHlabs/multiSPAETI
Project-URL: Issues, https://github.com/HiDiHlabs/multiSPAETI/issues
Classifier: Intended Audience :: Science/Research
Classifier: License :: OSI Approved :: MIT License
Classifier: Programming Language :: Python
Classifier: Programming Language :: Python :: 3
Classifier: Programming Language :: Python :: 3 :: Only
Classifier: Topic :: Scientific/Engineering
Classifier: Typing :: Typed
Requires-Python: >=3.11
License-File: LICENSE
Requires-Dist: numpy>=1.25
Requires-Dist: scikit-learn>=1.6
Requires-Dist: scipy>=1.11
Provides-Extra: cuda11
Requires-Dist: cupy-cuda11x>=13; extra == "cuda11"
Provides-Extra: cuda12
Requires-Dist: cupy-cuda12x>=13; extra == "cuda12"
Provides-Extra: plot
Requires-Dist: matplotlib>=3.8; extra == "plot"
Provides-Extra: test
Requires-Dist: pytest; extra == "test"
Provides-Extra: docs
Requires-Dist: sphinx; extra == "docs"
Requires-Dist: sphinx-copybutton; extra == "docs"
Requires-Dist: sphinx-rtd-theme; extra == "docs"
Provides-Extra: dev
Requires-Dist: multispaeti[docs,plot,test]; extra == "dev"
Requires-Dist: pre-commit; extra == "dev"
Dynamic: license-file
